Workbook
Name Aporte: APP!$E$19
Name dividendos_mensais: APP!$E$23
Name investimento_mensal_A: APP!$C$35
Name investimento_mensal_B: APP!$D$35
Name patrimonio: APP!$E$22
Name patrimonio_final_A: APP!$C$39
Name patrimonio_final_B: APP!$D$39
Name Prazo_anos_A: APP!$C$36
Name Prazo_anos_B: APP!$D$36
Name qtd_anos: APP!$E$20
Name Rendimento_carteira: APP!$E$15
Name salario: APP!$E$14
Name sugestao_investimento: APP!$E$16
Name taxa_mensal: APP!$E$21
Name taxa_mensal_A: APP!$C$37
Name taxa_mensal_B: APP!$D$37
Name Total_aportado_A: APP!$C$38
Name Total_aportado_B: APP!$D$38

Sheet APP
B13: Configurações
B14: Salário | E14: 5000
B15: Rendimento Carteira | E15: 0.006
B16: Sugestão de Investimento (30%) | E16: =salario*30% -> 1500
B18: Investimento mensal
B19: Quanto investir por mês? | E19: 1500
B20: Por quantos anos? | E20: 5
B21: Taxa de rendimento mensal? | E21: 0.01079
B22: Patrimônio acumulado? | E22: =FV(taxa_mensal,qtd_anos*12,Aporte*-1) -> 125665.37
B23: Dividendos mensais? | E23: =patrimonio*Rendimento_carteira -> 753.99223
B25: Cenários
B26: Anos | D26: Patrimônio acumulado | E26: Dividendos mensais
B27: 2 | D27: =FV(taxa_mensal,$B27*12,Aporte*-1) -> 40841.441 | E27: =D27*Rendimento_carteira -> 245.04865
B28: 5 | D28: =FV(taxa_mensal,$B28*12,Aporte*-1) -> 125665.37 | E28: =D28*Rendimento_carteira -> 753.99223
B29: 10 | D29: =FV(taxa_mensal,$B29*12,Aporte*-1) -> 364926.32 | E29: =D29*Rendimento_carteira -> 2189.5579
B30: 20 | D30: =FV(taxa_mensal,$B30*12,Aporte*-1) -> 1687797.6 | E30: =D30*Rendimento_carteira -> 10126.786
B31: 30 | D31: =FV(taxa_mensal,$B31*12,Aporte*-1) -> 6483254.5 | E31: =D31*Rendimento_carteira -> 38899.527
B33: Comparador de cenários
B34: Indicador | C34: Cenário A | D34: Cenário B | E34: Melhor Resultado
B35: Investimento mensal | C35: 1500 | D35: 1500 | E35: -
B36: Prazo (anos) | C36: 2 | D36: 5 | E36: -
B37: Taxa mensal | C37: 0.0108 | D37: 0.0108 | E37: {=_xlfn.IFS(C37>D37,"Cenário A",C37<D37,"Cenário B",C37=D37,"Igual")} -> Igual
B38: Total aportado | C38: =investimento_mensal_A*Prazo_anos_A*12 -> 36000 | D38: =investimento_mensal_B*Prazo_anos_B*12 -> 90000 | E38: -
B39: Patrimônio final | C39: =FV(taxa_mensal_A,Prazo_anos_A*12,investimento_mensal_A*-1) -> 40846.295 | D39: =FV(taxa_mensal_B,Prazo_anos_B*12,investimento_mensal_B*-1) -> 125706.03 | E39: {=_xlfn.IFS(C39>D39,"Cenário A",C39<D39,"Cenário B",C39=D39,"Igual")} -> Cenário B
B40: Dividendos mensais | C40: =patrimonio_final_A*Rendimento_carteira -> 245.07777 | D40: =patrimonio_final_B*Rendimento_carteira -> 754.23617 | E40: {=_xlfn.IFS(C40>D40,"Cenário A",C40<D40,"Cenário B",C40=D40,"Igual")} -> Cenário B
B42: PERFIL | D42: MODERADO
B43: VALOR A SER INVESTIDO POR MÊS | D43: =Aporte -> 1500
B45: TIPO DE FII | D45: Percentual Sugerido | E45: Valores
B46: PAPEL | D46: =VLOOKUP($D$42&"-"&B46,'Base de dados'!B:E,4,) -> 0.32 | E46: =Aporte*D46 -> 480
B47: TIJOLO | D47: =VLOOKUP($D$42&"-"&B47,'Base de dados'!B:E,4,) -> 0.35 | E47: =Aporte*D47 -> 525
B48: HÍBRIDOS | D48: =VLOOKUP($D$42&"-"&B48,'Base de dados'!B:E,4,) -> 0.08 | E48: =Aporte*D48 -> 120
B49: FOFs | D49: =VLOOKUP($D$42&"-"&B49,'Base de dados'!B:E,4,) -> 0.05 | E49: =Aporte*D49 -> 75
B50: DESENVOLVIMENTO | D50: =VLOOKUP($D$42&"-"&B50,'Base de dados'!B:E,4,) -> 0.1 | E50: =Aporte*D50 -> 150
B51: HOTELARIAS | D51: =VLOOKUP($D$42&"-"&B51,'Base de dados'!B:E,4,) -> 0.1 | E51: =Aporte*D51 -> 150
E52: =SUM(E46:E51) -> 1500

Sheet Base de dados
B2: CHAVE | C2: PERFIL | D2: TIPO DE FII | E2: PERCENTUAL
B3: =$C$3&"-"&D3 -> Conservador-PAPEL | C3: Conservador | D3: PAPEL | E3: 0.3
B4: =$C$3&"-"&D4 -> Conservador-TIJOLO | C4: Conservador | D4: TIJOLO | E4: 0.5
B5: =$C$3&"-"&D5 -> Conservador-HÍBRIDOS | C5: Conservador | D5: HÍBRIDOS | E5: 0.1
B6: =$C$3&"-"&D6 -> Conservador-FOFs | C6: Conservador | D6: FOFs | E6: 0.1
B7: =$C$3&"-"&D7 -> Conservador-DESENVOLVIMENTO | C7: Conservador | D7: DESENVOLVIMENTO | E7: 0
B8: =$C$3&"-"&D8 -> Conservador-HOTELARIAS | C8: Conservador | D8: HOTELARIAS | E8: 0
B9: =$C$9&"-"&D9 -> Moderado-PAPEL | C9: Moderado | D9: PAPEL | E9: 0.32
B10: =$C$9&"-"&D10 -> Moderado-TIJOLO | C10: Moderado | D10: TIJOLO | E10: 0.35
B11: =$C$9&"-"&D11 -> Moderado-HÍBRIDOS | C11: Moderado | D11: HÍBRIDOS | E11: 0.08
B12: =$C$9&"-"&D12 -> Moderado-FOFs | C12: Moderado | D12: FOFs | E12: 0.05
B13: =$C$9&"-"&D13 -> Moderado-DESENVOLVIMENTO | C13: Moderado | D13: DESENVOLVIMENTO | E13: 0.1
B14: =$C$9&"-"&D14 -> Moderado-HOTELARIAS | C14: Moderado | D14: HOTELARIAS | E14: 0.1
B15: =$C$15&"-"&D15 -> Agressivo-PAPEL | C15: Agressivo | D15: PAPEL | E15: 0.5
B16: =$C$15&"-"&D16 -> Agressivo-TIJOLO | C16: Agressivo | D16: TIJOLO | E16: 0.1
B17: =$C$15&"-"&D17 -> Agressivo-HÍBRIDOS | C17: Agressivo | D17: HÍBRIDOS | E17: 0.05
B18: =$C$15&"-"&D18 -> Agressivo-FOFs | C18: Agressivo | D18: FOFs | E18: 0.05
B19: =$C$15&"-"&D19 -> Agressivo-DESENVOLVIMENTO | C19: Agressivo | D19: DESENVOLVIMENTO | E19: 0.2
B20: =$C$15&"-"&D20 -> Agressivo-HOTELARIAS | C20: Agressivo | D20: HOTELARIAS | E20: 0.1
